beancount_ethereum/__init__.py
beancount_ethereum/__main__.py
beancount_ethereum/downloader.py
beancount_ethereum/importer.py
beancount_ethereum-1.4.3.dist-info/LICENSE
beancount_ethereum-1.4.3.dist-info/METADATA
beancount_ethereum-1.4.3.dist-info/WHEEL
beancount_ethereum-1.4.3.dist-info/entry_points.txt
beancount_ethereum-1.4.3.dist-info/top_level.txt
beancount_ethereum-1.4.3.dist-info/RECORD
