Metadata-Version: 2.1
Name: beancount-ethereum
Version: 1.4.3
Summary: Ethereum transaction importer for Beancount
Home-page: https://github.com/xuhcc/beancount-ethereum-importer
Download-URL: https://github.com/xuhcc/beancount-ethereum-importer
Author: xuhcc
License: GPLv3
Requires-Python: >=3.6
License-File: LICENSE
Requires-Dist: beancount
